swarmauri_certs_composite/CompositeCertService.py
swarmauri_certs_composite/__init__.py
swarmauri_certs_composite-0.3.0.dev5.dist-info/LICENSE
swarmauri_certs_composite-0.3.0.dev5.dist-info/METADATA
swarmauri_certs_composite-0.3.0.dev5.dist-info/WHEEL
swarmauri_certs_composite-0.3.0.dev5.dist-info/entry_points.txt
swarmauri_certs_composite-0.3.0.dev5.dist-info/RECORD
